pyasn1-stubs/METADATA.toml
pyasn1-stubs/__init__.pyi
pyasn1-stubs/debug.pyi
pyasn1-stubs/error.pyi
pyasn1-stubs/py.typed
pyasn1-stubs/codec/__init__.pyi
pyasn1-stubs/codec/streaming.pyi
pyasn1-stubs/codec/ber/__init__.pyi
pyasn1-stubs/codec/ber/decoder.pyi
pyasn1-stubs/codec/ber/encoder.pyi
pyasn1-stubs/codec/ber/eoo.pyi
pyasn1-stubs/codec/cer/__init__.pyi
pyasn1-stubs/codec/cer/decoder.pyi
pyasn1-stubs/codec/cer/encoder.pyi
pyasn1-stubs/codec/der/__init__.pyi
pyasn1-stubs/codec/der/decoder.pyi
pyasn1-stubs/codec/der/encoder.pyi
pyasn1-stubs/codec/native/__init__.pyi
pyasn1-stubs/codec/native/decoder.pyi
pyasn1-stubs/codec/native/encoder.pyi
pyasn1-stubs/compat/__init__.pyi
pyasn1-stubs/compat/integer.pyi
pyasn1-stubs/type/__init__.pyi
pyasn1-stubs/type/base.pyi
pyasn1-stubs/type/char.pyi
pyasn1-stubs/type/constraint.pyi
pyasn1-stubs/type/error.pyi
pyasn1-stubs/type/namedtype.pyi
pyasn1-stubs/type/namedval.pyi
pyasn1-stubs/type/opentype.pyi
pyasn1-stubs/type/tag.pyi
pyasn1-stubs/type/tagmap.pyi
pyasn1-stubs/type/univ.pyi
pyasn1-stubs/type/useful.pyi
types_pyasn1-0.6.0.20250516.dist-info/licenses/LICENSE
types_pyasn1-0.6.0.20250516.dist-info/METADATA
types_pyasn1-0.6.0.20250516.dist-info/WHEEL
types_pyasn1-0.6.0.20250516.dist-info/top_level.txt
types_pyasn1-0.6.0.20250516.dist-info/RECORD
